fastapi_pypi_proxy/__init__.py
fastapi_pypi_proxy-0.0.2.dist-info/LICENSE
fastapi_pypi_proxy-0.0.2.dist-info/METADATA
fastapi_pypi_proxy-0.0.2.dist-info/WHEEL
fastapi_pypi_proxy-0.0.2.dist-info/top_level.txt
fastapi_pypi_proxy-0.0.2.dist-info/RECORD
