Metadata-Version: 2.1
Name: fastapi-pypi-proxy
Version: 0.0.2
Summary: A pypi proxy using fastapi
Home-page: https://github.com/singingplayer/fastapi-pypi-proxy
Author: xyzou
Author-email: zouxinyin1992@163.com
License: UNKNOWN
Platform: UNKNOWN
Requires-Python: >3.6.0
Requires-Dist: aiocontextvars (==0.2.2)
Requires-Dist: aiofiles (==0.6.0)
Requires-Dist: certifi (==2020.12.5)
Requires-Dist: chardet (==4.0.0)
Requires-Dist: click (==7.1.2)
Requires-Dist: colorama (==0.4.4)
Requires-Dist: contextvars (==2.4)
Requires-Dist: dataclasses (==0.6)
Requires-Dist: fastapi (==0.63.0)
Requires-Dist: h11 (==0.12.0)
Requires-Dist: idna (==2.10)
Requires-Dist: immutables (==0.14)
Requires-Dist: loguru (==0.5.3)
Requires-Dist: pydantic (==1.7.3)
Requires-Dist: requests (==2.25.1)
Requires-Dist: starlette (==0.13.6)
Requires-Dist: typing-extensions (==3.7.4.3)
Requires-Dist: urllib3 (==1.26.2)
Requires-Dist: uvicorn (==0.13.3)
Requires-Dist: win32-setctime (==1.0.3)
